<?xml version="1.0"?>
<opencv_storage>
<layers>
<layer-0>
	<type>InputData</type>
	<name>input1</name>
	<n_input_planes>2</n_input_planes> <!-- number of values to add -->
	<input_height>10</input_height>    <!-- decimal -->
	<input_width>1</input_width>
	<seq_length>3</seq_length>         <!-- three digits -->
</layer-0>
<layer-1>
	<type>ImgCropping</type>
	<name>crop1</name>
	<input_layer>input1</input_layer>
	<n_output_planes>2</n_output_planes>
	<output_height>10</output_height>
	<output_width>1</output_width>
	<seq_length>1</seq_length>
	<time_index>0</time_index>
	<activation_type>tanh</activation_type>
</layer-1>
<layer-2>
	<type>Recurrent</type>
	<name>rnn1</name>
	<n_hiddens>20</n_hiddens>
	<n_output_planes>10</n_output_planes>
	<seq_length>3</seq_length>
	<time_index>0</time_index>
	<activation_type>tanh</activation_type>
</layer-2>
<layer-3> <predefined>crop1</predefined><time_index>1</time_index></layer-3> 
<layer-4> <predefined>rnn1</predefined> <time_index>1</time_index></layer-4>
<layer-5> <predefined>crop1</predefined><time_index>2</time_index></layer-5> 
<layer-6> <predefined>rnn1</predefined> <time_index>2</time_index></layer-6>
</layers>
</opencv_storage>
